tripswitch/__init__.py
tripswitch/backend.py
tripswitch/py.typed
tripswitch/tripswitch.py
tripswitch-0.0.1.dev1.dist-info/METADATA
tripswitch-0.0.1.dev1.dist-info/WHEEL
tripswitch-0.0.1.dev1.dist-info/top_level.txt
tripswitch-0.0.1.dev1.dist-info/RECORD
