Metadata-Version: 2.2
Name: tripswitch
Version: 0.0.1.dev1
Summary: A Python Circuit Breaker implementation
Author-email: Scott Houseman <scott@houseman.co.za>
License: MIT License
Project-URL: repository, https://github.com/houseman/tripswitch
Classifier: Development Status :: 3 - Alpha
Classifier: Intended Audience :: Developers
Classifier: License :: OSI Approved :: MIT License
Classifier: Operating System :: OS Independent
Classifier: Programming Language :: Python :: 3
Classifier: Programming Language :: Python :: 3.9
Classifier: Programming Language :: Python :: 3.10
Classifier: Programming Language :: Python :: 3.11
Classifier: Programming Language :: Python :: 3.12
Classifier: Programming Language :: Python :: 3.13
Classifier: Programming Language :: Python :: 3 :: Only
Classifier: Topic :: Software Development :: Libraries :: Python Modules
Classifier: Typing :: Typed
Requires-Python: >=3.9
Requires-Dist: circuitbreaker>=2.0.0
Requires-Dist: typing-extensions>=4.12.2
Provides-Extra: redis
Requires-Dist: redis>=5.2.1; extra == "redis"
Provides-Extra: valkey
Requires-Dist: valkey>=6.1.0; extra == "valkey"
Provides-Extra: memcache
Requires-Dist: pymemcache>=4.0.0; extra == "memcache"
Provides-Extra: all
Requires-Dist: redis>=5.2.1; extra == "all"
Requires-Dist: valkey>=6.1.0; extra == "all"
Requires-Dist: pymemcache>=4.0.0; extra == "all"
